setup.py
brb/__init__.py
brb/cache.py
brb.egg-info/PKG-INFO
brb.egg-info/SOURCES.txt
brb.egg-info/dependency_links.txt
brb.egg-info/not-zip-safe
brb.egg-info/top_level.txt