Metadata-Version: 1.0
Name: brb
Version: 0.0.1
Summary: Be Right Back: cache your functions
Home-page: http://github.com/lazywei/brb
Author: Chih-Wei Chang
Author-email: bert.cwchang@gmail.com
License: MIT
Platform: UNKNOWN
